{"league":{"id":"sr:competition:771","name":"Liga-V 2","gender":"men","league_id":"771","slug":"liga-v-2","country_info":{"name":"Vietname","slug":"vietname","icon":"/logos/countries/default-flag.svg"},"icon":"/logos/leagues-v2/771.png"},"sport":"futebol","seasons":[{"start_date":"2022-03-04","end_date":"2022-11-30","year":"2022","id":"sr:season:90271","competition_id":"sr:competition:771","name":"Liga-V 2 2022","season_id":"90271","league_id":"771","slug":"liga-v-2-2022","icon":"/logos/leagues/vietname_liga-v 2 2022.png","start_date_formatted":"sexta, 04 mar 2022","end_date_formatted":"quarta, 30 nov 2022","season_progress":63},{"start_date":"2021-03-19","end_date":"2021-09-19","year":"2021","id":"sr:season:82150","competition_id":"sr:competition:771","name":"Liga-V 2 2021","season_id":"82150","league_id":"771","slug":"liga-v-2-2021","icon":"/logos/leagues/vietname_liga-v 2 2021.png","start_date_formatted":"sexta, 19 mar 2021","end_date_formatted":"domingo, 19 set 2021","season_progress":100},{"start_date":"2020-02-29","end_date":"2020-11-02","year":"2020","id":"sr:season:74969","competition_id":"sr:competition:771","name":"Liga-V 2 2020","season_id":"74969","league_id":"771","slug":"liga-v-2-2020","icon":"/logos/leagues/vietname_liga-v 2 2020.png","start_date_formatted":"sábado, 29 fev 2020","end_date_formatted":"segunda, 02 nov 2020","season_progress":100}],"current_season":{"start_date":"2022-03-04","end_date":"2022-11-30","year":"2022","id":"sr:season:90271","competition_id":"sr:competition:771","name":"Liga-V 2 2022","season_id":"90271","league_id":"771","slug":"liga-v-2-2022","icon":"/logos/leagues/vietname_liga-v 2 2022.png","start_date_formatted":"sexta, 04 mar 2022","end_date_formatted":"quarta, 30 nov 2022","season_progress":63},"current_season_teams":[{"short_name":"Long An FC","abbreviation":"LON","name":"Long An FC","id":"33122","team_id":"33122","icon":"/logos/teams-v2/33122.png","slug":"long-an-fc","form":["-","-","-","-","-"]},{"short_name":"Khan Hoa","abbreviation":"HOA","name":"Khan Hoa","id":"33126","team_id":"33126","icon":"/logos/teams-v2/33126.png","slug":"khan-hoa","form":["-","-","-","-","-"]},{"short_name":"Can Tho FC","abbreviation":"THO","name":"Can Tho FC","id":"38225","team_id":"38225","icon":"/logos/teams-v2/38225.png","slug":"can-tho-fc","form":["-","-","-","-","-"]},{"short_name":"Quang Nam FC","abbreviation":"QUA","name":"Quang Nam FC","id":"40018","team_id":"40018","icon":"/logos/teams-v2/40018.png","slug":"quang-nam-fc","form":["-","-","-","-","-"]},{"short_name":"Clb Bong Da Hue","abbreviation":"HUE","name":"Clb Bong Da Hue","id":"40023","team_id":"40023","icon":"/logos/teams-v2/40023.png","slug":"clb-bong-da-hue","form":["-","-","-","-","-"]},{"short_name":"Dak Lak","abbreviation":"DAL","name":"Dak Lak","id":"143848","team_id":"143848","icon":"/logos/teams-v2/143848.png","slug":"dak-lak","form":["-","-","-","-","-"]},{"short_name":"Cong An Nhan Dan","abbreviation":"CND","name":"Cong An Nhan Dan","id":"196371","team_id":"196371","icon":"/logos/teams-v2/196371.png","slug":"cong-an-nhan-dan","form":["-","-","-","-","-"]},{"short_name":"Binh Phouc","abbreviation":"BIP","name":"Binh Phouc","id":"200173","team_id":"200173","icon":"/logos/teams-v2/200173.png","slug":"binh-phouc","form":["-","-","-","-","-"]},{"short_name":"Phu Dong FC","abbreviation":"PHU","name":"Phu Dong FC","id":"330079","team_id":"330079","icon":"/logos/teams-v2/330079.png","slug":"phu-dong-fc","form":["-","-","-","-","-"]},{"short_name":"Pho Hien FC","abbreviation":"PHI","name":"Pho Hien FC","id":"340516","team_id":"340516","icon":"/logos/teams-v2/340516.png","slug":"pho-hien-fc","form":["-","-","-","-","-"]},{"short_name":"Ba Ria Vung Tau FC","abbreviation":"RIA","name":"Ba Ria Vung Tau FC","id":"557448","team_id":"557448","icon":"/logos/teams-v2/557448.png","slug":"ba-ria-vung-tau-fc","form":["-","-","-","-","-"]},{"short_name":"Phu Tho FC","abbreviation":"PHU","name":"Phu Tho FC","id":"729127","team_id":"729127","icon":"/logos/teams-v2/729127.png","slug":"phu-tho-fc","form":["-","-","-","-","-"]}],"summary_text":"Liga-V 2, também conhecida como, Liga-V 2 2022, é a liga de futebol profissional no(a) Vietname para men. Existem ao todo 12 times que competem pelo título todos os anos entre 04/03/2022 to 30/11/2022"}