{"league":{"id":"sr:competition:14457","name":"Liga Nacional","gender":"men","league_id":"14457","slug":"liga-nacional","country_info":{"id":152,"continent":"América do Sul","name":"Chile","alpha2":"cl","alpha3":"chl","slug":"chile","icon":"/logos/countries/cl.svg"},"icon":"/logos/leagues-v2/14457.png"},"sport":"basquete","seasons":[{"start_date":"2022-01-08","end_date":"2022-09-30","year":"2022","id":"sr:season:90169","competition_id":"sr:competition:14457","name":"Liga Nacional 2022","season_id":"90169","league_id":"14457","slug":"liga-nacional-2022","icon":"/logos/leagues/américa do sul_chile_liga nacional 2022.png","start_date_formatted":"sábado, 08 jan 2022","end_date_formatted":"sexta, 30 set 2022","season_progress":85},{"start_date":"2021-02-01","end_date":"2021-09-12","year":"2021","id":"sr:season:81512","competition_id":"sr:competition:14457","name":"Liga Nacional 2021","season_id":"81512","league_id":"14457","slug":"liga-nacional-2021","icon":"/logos/leagues/américa do sul_chile_liga nacional 2021.png","start_date_formatted":"segunda, 01 fev 2021","end_date_formatted":"domingo, 12 set 2021","season_progress":100},{"start_date":"2019-10-04","end_date":"2020-06-01","year":"19/20","id":"sr:season:71730","competition_id":"sr:competition:14457","name":"Liga Nacional 19/20","season_id":"71730","league_id":"14457","slug":"liga-nacional-19-20","icon":"/logos/leagues/américa do sul_chile_liga nacional 19 20.png","start_date_formatted":"sexta, 04 out 2019","end_date_formatted":"segunda, 01 jun 2020","season_progress":100}],"current_season":{"start_date":"2022-01-08","end_date":"2022-09-30","year":"2022","id":"sr:season:90169","competition_id":"sr:competition:14457","name":"Liga Nacional 2022","season_id":"90169","league_id":"14457","slug":"liga-nacional-2022","icon":"/logos/leagues/américa do sul_chile_liga nacional 2022.png","start_date_formatted":"sábado, 08 jan 2022","end_date_formatted":"sexta, 30 set 2022","season_progress":85},"current_season_teams":[{"short_name":"Leones de Quilpue","abbreviation":"LQU","name":"Leones de Quilpue","id":"134420","team_id":"134420","icon":"/logos/teams-v2/134420.png","slug":"leones-de-quilpue","form":["-","-","-","-","-"]},{"short_name":"Deportivo Tinguiririca São Fernando","abbreviation":"TIN","name":"Deportivo Tinguiririca São Fernando","id":"177630","team_id":"177630","icon":"/logos/teams-v2/177630.png","slug":"deportivo-tinguiririca-são-fernando","form":["-","-","-","-","-"]},{"short_name":"CD Castro","abbreviation":"CAS","name":"CD Castro","id":"227872","team_id":"227872","icon":"/logos/teams-v2/227872.png","slug":"cd-castro","form":["-","-","-","-","-"]},{"short_name":"CD Valdivia","abbreviation":"VAL","name":"CD Valdivia","id":"284871","team_id":"284871","icon":"/logos/teams-v2/284871.png","slug":"cd-valdivia","form":["-","-","-","-","-"]},{"short_name":"CD Universidade de Concepion","abbreviation":"UNI","name":"CD Universidade de Concepion","id":"284879","team_id":"284879","icon":"/logos/teams-v2/284879.png","slug":"cd-universidade-de-concepion","form":["-","-","-","-","-"]},{"short_name":"CD Puente Alto","abbreviation":"PUE","name":"CD Puente Alto","id":"289247","team_id":"289247","icon":"/logos/teams-v2/289247.png","slug":"cd-puente-alto","form":["-","-","-","-","-"]},{"short_name":"CD Universidade Católica de Santiago","abbreviation":"UNI","name":"CD Universidade Católica de Santiago","id":"289249","team_id":"289249","icon":"/logos/teams-v2/289249.png","slug":"cd-universidade-católica-de-santiago","form":["-","-","-","-","-"]},{"short_name":"CD Las Animas","abbreviation":"LAS","name":"CD Las Animas","id":"289251","team_id":"289251","icon":"/logos/teams-v2/289251.png","slug":"cd-las-animas","form":["-","-","-","-","-"]},{"short_name":"Aba Ancud","abbreviation":"ANC","name":"Aba Ancud","id":"289255","team_id":"289255","icon":"/logos/teams-v2/289255.png","slug":"aba-ancud","form":["-","-","-","-","-"]},{"short_name":"CD Espanol de Talca","abbreviation":"ESP","name":"CD Espanol de Talca","id":"289563","team_id":"289563","icon":"/logos/teams-v2/289563.png","slug":"cd-espanol-de-talca","form":["-","-","-","-","-"]},{"short_name":"CEB Puerto Montt","abbreviation":"CEB","name":"CEB Puerto Montt","id":"290750","team_id":"290750","icon":"/logos/teams-v2/290750.png","slug":"ceb-puerto-montt","form":["-","-","-","-","-"]},{"short_name":"CD Atlético Puerto Varas","abbreviation":"ATL","name":"CD Atlético Puerto Varas","id":"507398","team_id":"507398","icon":"/logos/teams-v2/507398.png","slug":"cd-atlético-puerto-varas","form":["-","-","-","-","-"]},{"short_name":"CD AB Temuco","abbreviation":"TEM","name":"CD AB Temuco","id":"507640","team_id":"507640","icon":"/logos/teams-v2/507640.png","slug":"cd-ab-temuco","form":["-","-","-","-","-"]}],"summary_text":"Liga Nacional, também conhecida como, Liga Nacional 2022, é a liga de basquete profissional no(a) Chile para men. Existem ao todo 13 times que competem pelo título todos os anos entre 08/01/2022 to 30/09/2022"}