{"league":{"id":"sr:competition:721","name":"Liga Prva","gender":"men","league_id":"721","slug":"liga-prva","country_info":{"id":688,"continent":"Europa","name":"Sérvia","alpha2":"rs","alpha3":"srb","slug":"sérvia","icon":"/logos/countries/rs.svg"},"icon":"/logos/leagues-v2/721.png"},"sport":"futebol","seasons":[{"start_date":"2022-07-30","end_date":"2023-05-27","year":"22/23","id":"sr:season:94771","competition_id":"sr:competition:721","name":"Liga Prva 22/23","season_id":"94771","league_id":"721","slug":"liga-prva-22-23","icon":"/logos/leagues/europa_sérvia_liga prva 22 23.png","start_date_formatted":"sábado, 30 jul 2022","end_date_formatted":"sábado, 27 mai 2023","season_progress":7.6},{"start_date":"2021-08-06","end_date":"2022-05-31","year":"21/22","id":"sr:season:84480","competition_id":"sr:competition:721","name":"Liga Prva 21/22","season_id":"84480","league_id":"721","slug":"liga-prva-21-22","icon":"/logos/leagues/europa_sérvia_liga prva 21 22.png","start_date_formatted":"sexta, 06 ago 2021","end_date_formatted":"terça, 31 mai 2022","season_progress":100},{"start_date":"2020-08-14","end_date":"2021-05-19","year":"20/21","id":"sr:season:77455","competition_id":"sr:competition:721","name":"Liga Prva 20/21","season_id":"77455","league_id":"721","slug":"liga-prva-20-21","icon":"/logos/leagues/europa_sérvia_liga prva 20 21.png","start_date_formatted":"sexta, 14 ago 2020","end_date_formatted":"quarta, 19 mai 2021","season_progress":100}],"current_season":{"start_date":"2022-07-30","end_date":"2023-05-27","year":"22/23","id":"sr:season:94771","competition_id":"sr:competition:721","name":"Liga Prva 22/23","season_id":"94771","league_id":"721","slug":"liga-prva-22-23","icon":"/logos/leagues/europa_sérvia_liga prva 22 23.png","start_date_formatted":"sábado, 30 jul 2022","end_date_formatted":"sábado, 27 mai 2023","season_progress":7.6},"current_season_teams":[{"short_name":"FK Rad","abbreviation":"RAD","name":"FK Rad","id":"5165","team_id":"5165","icon":"/logos/teams-v2/5165.png","slug":"fk-rad","form":["-","-","-","-","-"]},{"short_name":"RFK Novi Sad 1921","abbreviation":"NSA","name":"RFK Novi Sad 1921","id":"25727","team_id":"25727","icon":"/logos/teams-v2/25727.png","slug":"rfk-novi-sad-1921","form":["-","-","-","-","-"]},{"short_name":"FK Metalac GM","abbreviation":"MET","name":"FK Metalac GM","id":"25731","team_id":"25731","icon":"/logos/teams-v2/25731.png","slug":"fk-metalac-gm","form":["-","-","-","-","-"]},{"short_name":"FK Sloboda Uzice","abbreviation":"SLP","name":"FK Sloboda Uzice","id":"25733","team_id":"25733","icon":"/logos/teams-v2/25733.png","slug":"fk-sloboda-uzice","form":["-","-","-","-","-"]},{"short_name":"FK Indjija","abbreviation":"IND","name":"FK Indjija","id":"35326","team_id":"35326","icon":"/logos/teams-v2/35326.png","slug":"fk-indjija","form":["-","-","-","-","-"]},{"short_name":"FK Proleter Novi Sad","abbreviation":"PRO","name":"FK Proleter Novi Sad","id":"37130","team_id":"37130","icon":"/logos/teams-v2/37130.png","slug":"fk-proleter-novi-sad","form":["-","-","-","-","-"]},{"short_name":"FK Macva Sabac","abbreviation":"MAC","name":"FK Macva Sabac","id":"56019","team_id":"56019","icon":"/logos/teams-v2/56019.png","slug":"fk-macva-sabac","form":["-","-","-","-","-"]},{"short_name":"FK Radnicki Sremska Mitrovica","abbreviation":"RSM","name":"FK Radnicki Sremska Mitrovica","id":"117500","team_id":"117500","icon":"/logos/teams-v2/117500.png","slug":"fk-radnicki-sremska-mitrovica","form":["-","-","-","-","-"]},{"short_name":"FK Loznica","abbreviation":"LOZ","name":"FK Loznica","id":"207943","team_id":"207943","icon":"/logos/teams-v2/207943.png","slug":"fk-loznica","form":["-","-","-","-","-"]},{"short_name":"FK Trajal Krusevac","abbreviation":"TRK","name":"FK Trajal Krusevac","id":"273511","team_id":"273511","icon":"/logos/teams-v2/273511.png","slug":"fk-trajal-krusevac","form":["-","-","-","-","-"]},{"short_name":"FK Zlatibor Cajetina","abbreviation":"ZLA","name":"FK Zlatibor Cajetina","id":"374926","team_id":"374926","icon":"/logos/teams-v2/374926.png","slug":"fk-zlatibor-cajetina","form":["-","-","-","-","-"]},{"short_name":"RFK Graficar Belgrado","abbreviation":"GBE","name":"RFK Graficar Belgrado","id":"382284","team_id":"382284","icon":"/logos/teams-v2/382284.png","slug":"rfk-graficar-belgrado","form":["-","-","-","-","-"]},{"short_name":"FK Jedinstvo UB","abbreviation":"JED","name":"FK Jedinstvo UB","id":"401285","team_id":"401285","icon":"/logos/teams-v2/401285.png","slug":"fk-jedinstvo-ub","form":["-","-","-","-","-"]},{"short_name":"FK Imt Novi Beograd","abbreviation":"IMT","name":"FK Imt Novi Beograd","id":"425691","team_id":"425691","icon":"/logos/teams-v2/425691.png","slug":"fk-imt-novi-beograd","form":["-","-","-","-","-"]},{"short_name":"FK Zeleznicar Pancevo","abbreviation":"ZEL","name":"FK Zeleznicar Pancevo","id":"425695","team_id":"425695","icon":"/logos/teams-v2/425695.png","slug":"fk-zeleznicar-pancevo","form":["-","-","-","-","-"]},{"short_name":"FK Radnicki Novi Belgrado","abbreviation":"RAB","name":"FK Radnicki Novi Belgrado","id":"522244","team_id":"522244","icon":"/logos/teams-v2/522244.png","slug":"fk-radnicki-novi-belgrado","form":["-","-","-","-","-"]},{"short_name":"OFK Vrsac","abbreviation":"OFK","name":"OFK Vrsac","id":"552141","team_id":"552141","icon":"/logos/teams-v2/552141.png","slug":"ofk-vrsac","form":["-","-","-","-","-"]}],"summary_text":"Liga Prva, também conhecida como, Liga Prva 22/23, é a liga de futebol profissional no(a) Sérvia para men. Existem ao todo 17 times que competem pelo título todos os anos entre 30/07/2022 to 27/05/2023"}