{"league":{"id":"sr:competition:23479","name":"Liga de Futebol Premier","gender":"men","league_id":"23479","slug":"liga-de-futebol-premier","country_info":{"id":0,"continent":"África","name":"Zimbabué","alpha2":"zw","alpha3":"zwb","slug":"zimbabué","icon":"/logos/countries/zw.svg"},"icon":"/logos/leagues-v2/23479.png"},"sport":"futebol","seasons":[{"start_date":"2021-11-01","end_date":"2022-07-31","year":"21/22","id":"sr:season:88591","competition_id":"sr:competition:23479","name":"Liga de Futebol Premier 21/22","season_id":"88591","league_id":"23479","slug":"liga-de-futebol-premier-21-22","icon":"/logos/leagues/áfrica_zimbabué_liga de futebol premier 21 22.png","start_date_formatted":"segunda, 01 nov 2021","end_date_formatted":"domingo, 31 jul 2022","season_progress":100},{"start_date":"2019-03-29","end_date":"2019-12-16","year":"2019","id":"sr:season:65144","competition_id":"sr:competition:23479","name":"Liga de Futebol Premier 2019","season_id":"65144","league_id":"23479","slug":"liga-de-futebol-premier-2019","icon":"/logos/leagues/áfrica_zimbabué_liga de futebol premier 2019.png","start_date_formatted":"sexta, 29 mar 2019","end_date_formatted":"segunda, 16 dez 2019","season_progress":100},{"start_date":"2018-03-17","end_date":"2018-11-25","year":"2018","id":"sr:season:51921","competition_id":"sr:competition:23479","name":"Liga de Futebol Premier 2018","season_id":"51921","league_id":"23479","slug":"liga-de-futebol-premier-2018","icon":"/logos/leagues/áfrica_zimbabué_liga de futebol premier 2018.png","start_date_formatted":"sábado, 17 mar 2018","end_date_formatted":"domingo, 25 nov 2018","season_progress":100}],"current_season":{"start_date":"2021-11-01","end_date":"2022-07-31","year":"21/22","id":"sr:season:88591","competition_id":"sr:competition:23479","name":"Liga de Futebol Premier 21/22","season_id":"88591","league_id":"23479","slug":"liga-de-futebol-premier-21-22","icon":"/logos/leagues/áfrica_zimbabué_liga de futebol premier 21 22.png","start_date_formatted":"segunda, 01 nov 2021","end_date_formatted":"domingo, 31 jul 2022","season_progress":100},"current_season_teams":[{"short_name":"Caps United FC","abbreviation":"CAP","name":"Caps United FC","id":"317569","team_id":"317569","icon":"/logos/teams-v2/317569.png","slug":"caps-united-fc","form":["-","-","-","-","-"]},{"short_name":"Ngezi Platinum","abbreviation":"NGE","name":"Ngezi Platinum","id":"317869","team_id":"317869","icon":"/logos/teams-v2/317869.png","slug":"ngezi-platinum","form":["-","-","-","-","-"]},{"short_name":"Yadah FC","abbreviation":"YAD","name":"Yadah FC","id":"325721","team_id":"325721","icon":"/logos/teams-v2/325721.png","slug":"yadah-fc","form":["-","-","-","-","-"]},{"short_name":"Dynamos Harare FC","abbreviation":"DYN","name":"Dynamos Harare FC","id":"332407","team_id":"332407","icon":"/logos/teams-v2/332407.png","slug":"dynamos-harare-fc","form":["-","-","-","-","-"]},{"short_name":"Cidade de Bulawayo","abbreviation":"BUL","name":"Cidade de Bulawayo","id":"380442","team_id":"380442","icon":"/logos/teams-v2/380442.png","slug":"cidade-de-bulawayo","form":["-","-","-","-","-"]},{"short_name":"Highlanders FC","abbreviation":"HIG","name":"Highlanders FC","id":"380444","team_id":"380444","icon":"/logos/teams-v2/380444.png","slug":"highlanders-fc","form":["-","-","-","-","-"]},{"short_name":"Cidade de Harare","abbreviation":"HAR","name":"Cidade de Harare","id":"380446","team_id":"380446","icon":"/logos/teams-v2/380446.png","slug":"cidade-de-harare","form":["-","-","-","-","-"]},{"short_name":"FC Platinum","abbreviation":"PLA","name":"FC Platinum","id":"412665","team_id":"412665","icon":"/logos/teams-v2/412665.png","slug":"fc-platinum","form":["-","-","-","-","-"]},{"short_name":"Black Rhinos FC","abbreviation":"BLA","name":"Black Rhinos FC","id":"421525","team_id":"421525","icon":"/logos/teams-v2/421525.png","slug":"black-rhinos-fc","form":["-","-","-","-","-"]},{"short_name":"Bulawayo Chiefs FC","abbreviation":"BUL","name":"Bulawayo Chiefs FC","id":"421527","team_id":"421527","icon":"/logos/teams-v2/421527.png","slug":"bulawayo-chiefs-fc","form":["-","-","-","-","-"]},{"short_name":"Chicken Inn","abbreviation":"CHI","name":"Chicken Inn","id":"421531","team_id":"421531","icon":"/logos/teams-v2/421531.png","slug":"chicken-inn","form":["-","-","-","-","-"]},{"short_name":"Herentals FC","abbreviation":"HER","name":"Herentals FC","id":"421535","team_id":"421535","icon":"/logos/teams-v2/421535.png","slug":"herentals-fc","form":["-","-","-","-","-"]},{"short_name":"Triangle United","abbreviation":"TRI","name":"Triangle United","id":"421545","team_id":"421545","icon":"/logos/teams-v2/421545.png","slug":"triangle-united","form":["-","-","-","-","-"]},{"short_name":"ZPC Kariba","abbreviation":"ZPC","name":"ZPC Kariba","id":"421547","team_id":"421547","icon":"/logos/teams-v2/421547.png","slug":"zpc-kariba","form":["-","-","-","-","-"]},{"short_name":"Manica Diamonds FC","abbreviation":"MAN","name":"Manica Diamonds FC","id":"551821","team_id":"551821","icon":"/logos/teams-v2/551821.png","slug":"manica-diamonds-fc","form":["-","-","-","-","-"]},{"short_name":"Cranborne Bullets FC","abbreviation":"CRA","name":"Cranborne Bullets FC","id":"840996","team_id":"840996","icon":"/logos/teams-v2/840996.png","slug":"cranborne-bullets-fc","form":["-","-","-","-","-"]},{"short_name":"Whawha FC","abbreviation":"WHA","name":"Whawha FC","id":"841008","team_id":"841008","icon":"/logos/teams-v2/841008.png","slug":"whawha-fc","form":["-","-","-","-","-"]},{"short_name":"Tenax CS FC","abbreviation":"TEN","name":"Tenax CS FC","id":"841010","team_id":"841010","icon":"/logos/teams-v2/841010.png","slug":"tenax-cs-fc","form":["-","-","-","-","-"]}],"summary_text":"Liga de Futebol Premier, também conhecida como, Liga de Futebol Premier 21/22, é a liga de futebol profissional no(a) Zimbabué para men. Existem ao todo 18 times que competem pelo título todos os anos entre 01/11/2021 to 31/07/2022"}