{"league":{"id":"sr:competition:1260","name":"Capital NPL 1","gender":"men","league_id":"1260","slug":"capital-npl-1","country_info":{"id":36,"continent":"Oceânia","name":"Austrália","alpha2":"au","alpha3":"aus","slug":"austrália","icon":"/logos/countries/au.svg"},"icon":"/logos/leagues-v2/1260.png"},"sport":"futebol","seasons":[{"start_date":"2022-04-01","end_date":"2022-12-31","year":"2022","id":"sr:season:91021","competition_id":"sr:competition:1260","name":"Capital NPL 1 2022","season_id":"91021","league_id":"1260","slug":"capital-npl-1-2022","icon":"/logos/leagues/oceânia_austrália_capital npl 1 2022.png","start_date_formatted":"sexta, 01 abr 2022","end_date_formatted":"sábado, 31 dez 2022","season_progress":52},{"start_date":"2021-04-10","end_date":"2021-12-31","year":"2021","id":"sr:season:81628","competition_id":"sr:competition:1260","name":"NPL, Capital Football 2021","season_id":"81628","league_id":"1260","slug":"npl-capital-football-2021","icon":"/logos/leagues/oceânia_austrália_npl, capital football 2021.png","start_date_formatted":"sábado, 10 abr 2021","end_date_formatted":"sexta, 31 dez 2021","season_progress":100},{"start_date":"2020-03-28","end_date":"2020-10-01","year":"2020","id":"sr:season:75019","competition_id":"sr:competition:1260","name":"NPL Capital Futebol 2020","season_id":"75019","league_id":"1260","slug":"npl-capital-futebol-2020","icon":"/logos/leagues/oceânia_austrália_npl capital futebol 2020.png","start_date_formatted":"sábado, 28 mar 2020","end_date_formatted":"quinta, 01 out 2020","season_progress":100}],"current_season":{"start_date":"2022-04-01","end_date":"2022-12-31","year":"2022","id":"sr:season:91021","competition_id":"sr:competition:1260","name":"Capital NPL 1 2022","season_id":"91021","league_id":"1260","slug":"capital-npl-1-2022","icon":"/logos/leagues/oceânia_austrália_capital npl 1 2022.png","start_date_formatted":"sexta, 01 abr 2022","end_date_formatted":"sábado, 31 dez 2022","season_progress":52},"current_season_teams":[{"short_name":"Belconnen United","abbreviation":"BEL","name":"Belconnen United","id":"91564","team_id":"91564","icon":"/logos/teams-v2/91564.png","slug":"belconnen-united","form":["-","-","-","-","-"]},{"short_name":"Canberra Croatia FC","abbreviation":"CAN","name":"Canberra Croatia FC","id":"91568","team_id":"91568","icon":"/logos/teams-v2/91568.png","slug":"canberra-croatia-fc","form":["-","-","-","-","-"]},{"short_name":"Canberra Olympic FC","abbreviation":"CAO","name":"Canberra Olympic FC","id":"91570","team_id":"91570","icon":"/logos/teams-v2/91570.png","slug":"canberra-olympic-fc","form":["-","-","-","-","-"]},{"short_name":"Cooma Tigers FC","abbreviation":"COO","name":"Cooma Tigers FC","id":"91572","team_id":"91572","icon":"/logos/teams-v2/91572.png","slug":"cooma-tigers-fc","form":["-","-","-","-","-"]},{"short_name":"Monaro Panthers FC","abbreviation":"MON","name":"Monaro Panthers FC","id":"91574","team_id":"91574","icon":"/logos/teams-v2/91574.png","slug":"monaro-panthers-fc","form":["-","-","-","-","-"]},{"short_name":"West Canberra Wanderers FC","abbreviation":"WCW","name":"West Canberra Wanderers FC","id":"91578","team_id":"91578","icon":"/logos/teams-v2/91578.png","slug":"west-canberra-wanderers-fc","form":["-","-","-","-","-"]},{"short_name":"Gungahlin United FC","abbreviation":"GUN","name":"Gungahlin United FC","id":"195356","team_id":"195356","icon":"/logos/teams-v2/195356.png","slug":"gungahlin-united-fc","form":["-","-","-","-","-"]},{"short_name":"O Connor Knights FC","abbreviation":"CON","name":"O Connor Knights FC","id":"607414","team_id":"607414","icon":"/logos/teams-v2/607414.png","slug":"o-connor-knights-fc","form":["-","-","-","-","-"]}],"summary_text":"Capital NPL 1, também conhecida como, Capital NPL 1 2022, é a liga de futebol profissional no(a) Austrália para men. Existem ao todo 8 times que competem pelo título todos os anos entre 01/04/2022 to 31/12/2022"}