{"league":{"id":"sr:competition:15327","name":"Taça da Federação","gender":"men","league_id":"15327","slug":"taça-da-federação","country_info":{"id":356,"continent":"Ásia","name":"India","alpha2":"in","alpha3":"ind","slug":"india","icon":"/logos/countries/in.svg"},"icon":"/logos/leagues-v2/15327.png"},"sport":"futebol","seasons":[{"start_date":"2017-05-07","end_date":"2017-06-30","year":"2017","id":"sr:season:40441","competition_id":"sr:competition:15327","name":"Taça das Federações 2017","season_id":"40441","league_id":"15327","slug":"taça-das-federações-2017","icon":"/logos/leagues/ásia_india_taça das federações 2017.png","start_date_formatted":"domingo, 07 mai 2017","end_date_formatted":"sexta, 30 jun 2017","season_progress":100}],"current_season":{"start_date":"2017-05-07","end_date":"2017-06-30","year":"2017","id":"sr:season:40441","competition_id":"sr:competition:15327","name":"Taça das Federações 2017","season_id":"40441","league_id":"15327","slug":"taça-das-federações-2017","icon":"/logos/leagues/ásia_india_taça das federações 2017.png","start_date_formatted":"domingo, 07 mai 2017","end_date_formatted":"sexta, 30 jun 2017","season_progress":100},"current_season_teams":[{"short_name":"Mohun Bagan AC","abbreviation":"MOH","name":"Mohun Bagan AC","id":"36354","team_id":"36354","icon":"/logos/teams-v2/36354.png","slug":"mohun-bagan-ac","form":["-","-","-","-","-"]},{"short_name":"Churchill Brothers SC","abbreviation":"CHB","name":"Churchill Brothers SC","id":"40078","team_id":"40078","icon":"/logos/teams-v2/40078.png","slug":"churchill-brothers-sc","form":["-","-","-","-","-"]},{"short_name":"SC East Bengal","abbreviation":"EBE","name":"SC East Bengal","id":"40655","team_id":"40655","icon":"/logos/teams-v2/40655.png","slug":"sc-east-bengal","form":["-","-","-","-","-"]},{"short_name":"Shillong Lajong FC","abbreviation":"LAJ","name":"Shillong Lajong FC","id":"58741","team_id":"58741","icon":"/logos/teams-v2/58741.png","slug":"shillong-lajong-fc","form":["-","-","-","-","-"]},{"short_name":"Bengaluru FC","abbreviation":"BEN","name":"Bengaluru FC","id":"118670","team_id":"118670","icon":"/logos/teams-v2/118670.png","slug":"bengaluru-fc","form":["-","-","-","-","-"]},{"short_name":"Aizawl FC","abbreviation":"AIZ","name":"Aizawl FC","id":"238586","team_id":"238586","icon":"/logos/teams-v2/238586.png","slug":"aizawl-fc","form":["-","-","-","-","-"]},{"short_name":"DSK Shivajians","abbreviation":"SHI","name":"DSK Shivajians","id":"238588","team_id":"238588","icon":"/logos/teams-v2/238588.png","slug":"dsk-shivajians","form":["-","-","-","-","-"]},{"short_name":"Cidade de Chennai","abbreviation":"CHN","name":"Cidade de Chennai","id":"307556","team_id":"307556","icon":"/logos/teams-v2/307556.png","slug":"cidade-de-chennai","form":["-","-","-","-","-"]}],"summary_text":"Taça da Federação, também conhecida como, Taça das Federações 2017, é a liga de futebol profissional no(a) India para men. Existem ao todo 8 times que competem pelo título todos os anos entre 07/05/2017 to 30/06/2017"}