{"league":{"id":"sr:competition:23745","name":"Taça da FA","gender":"men","league_id":"23745","slug":"taça-da-fa","country_info":{"id":458,"continent":"Ásia","name":"Malásia","alpha2":"my","alpha3":"mys","slug":"malásia","icon":"/logos/countries/my.svg"},"icon":"/logos/leagues-v2/23745.png"},"sport":"futebol","seasons":[{"start_date":"2022-03-11","end_date":"2022-09-17","year":"2022","id":"sr:season:91825","competition_id":"sr:competition:23745","name":"Taça da FA 2022","season_id":"91825","league_id":"23745","slug":"taça-da-fa-2022","icon":"/logos/leagues/ásia_malásia_taça da fa 2022.png","start_date_formatted":"sexta, 11 mar 2022","end_date_formatted":"sábado, 17 set 2022","season_progress":86},{"start_date":"2019-04-16","end_date":"2019-07-29","year":"2019","id":"sr:season:64041","competition_id":"sr:competition:23745","name":"Taça da FA 2019","season_id":"64041","league_id":"23745","slug":"taça-da-fa-2019","icon":"/logos/leagues/ásia_malásia_taça da fa 2019.png","start_date_formatted":"terça, 16 abr 2019","end_date_formatted":"segunda, 29 jul 2019","season_progress":100}],"current_season":{"start_date":"2022-03-11","end_date":"2022-09-17","year":"2022","id":"sr:season:91825","competition_id":"sr:competition:23745","name":"Taça da FA 2022","season_id":"91825","league_id":"23745","slug":"taça-da-fa-2022","icon":"/logos/leagues/ásia_malásia_taça da fa 2022.png","start_date_formatted":"sexta, 11 mar 2022","end_date_formatted":"sábado, 17 set 2022","season_progress":86},"current_season_teams":[{"short_name":"AF Kelantan","abbreviation":"KEL","name":"AF Kelantan","id":"3322","team_id":"3322","icon":"/logos/teams-v2/3322.png","slug":"af-kelantan","form":["-","-","-","-","-"]},{"short_name":"Selangor FC","abbreviation":"SEL","name":"Selangor FC","id":"3323","team_id":"3323","icon":"/logos/teams-v2/3323.png","slug":"selangor-fc","form":["-","-","-","-","-"]},{"short_name":"Kuala Lumpur City FC","abbreviation":"KUA","name":"Kuala Lumpur City FC","id":"3324","team_id":"3324","icon":"/logos/teams-v2/3324.png","slug":"kuala-lumpur-city-fc","form":["-","-","-","-","-"]},{"short_name":"Johor Darul Tazim FC","abbreviation":"JOH","name":"Johor Darul Tazim FC","id":"3327","team_id":"3327","icon":"/logos/teams-v2/3327.png","slug":"johor-darul-tazim-fc","form":["-","-","-","-","-"]},{"short_name":"Sabah FA","abbreviation":"SAB","name":"Sabah FA","id":"3329","team_id":"3329","icon":"/logos/teams-v2/3329.png","slug":"sabah-fa","form":["-","-","-","-","-"]},{"short_name":"Penang FA","abbreviation":"PEN","name":"Penang FA","id":"3330","team_id":"3330","icon":"/logos/teams-v2/3330.png","slug":"penang-fa","form":["-","-","-","-","-"]},{"short_name":"Nigeri Sembilan","abbreviation":"NEG","name":"Nigeri Sembilan","id":"3331","team_id":"3331","icon":"/logos/teams-v2/3331.png","slug":"nigeri-sembilan","form":["-","-","-","-","-"]},{"short_name":"Terengganu FC","abbreviation":"TER","name":"Terengganu FC","id":"3333","team_id":"3333","icon":"/logos/teams-v2/3333.png","slug":"terengganu-fc","form":["-","-","-","-","-"]},{"short_name":"Sarawak United FC","abbreviation":"SAU","name":"Sarawak United FC","id":"3334","team_id":"3334","icon":"/logos/teams-v2/3334.png","slug":"sarawak-united-fc","form":["-","-","-","-","-"]},{"short_name":"Melaka United SA","abbreviation":"MEU","name":"Melaka United SA","id":"3335","team_id":"3335","icon":"/logos/teams-v2/3335.png","slug":"melaka-united-sa","form":["-","-","-","-","-"]},{"short_name":"Kedah Darul Aman","abbreviation":"KDA","name":"Kedah Darul Aman","id":"3339","team_id":"3339","icon":"/logos/teams-v2/3339.png","slug":"kedah-darul-aman","form":["-","-","-","-","-"]},{"short_name":"Perak FC","abbreviation":"PER","name":"Perak FC","id":"61990","team_id":"61990","icon":"/logos/teams-v2/61990.png","slug":"perak-fc","form":["-","-","-","-","-"]},{"short_name":"Sri Pahang","abbreviation":"PAH","name":"Sri Pahang FA","id":"75279","team_id":"75279","icon":"/logos/teams-v2/75279.png","slug":"sri-pahang","form":["-","-","-","-","-"]},{"short_name":"AF PDRM","abbreviation":"PDR","name":"AF PDRM","id":"138874","team_id":"138874","icon":"/logos/teams-v2/138874.png","slug":"af-pdrm","form":["-","-","-","-","-"]},{"short_name":"UiTM FC","abbreviation":"UiTM","name":"UiTM FC","id":"240446","team_id":"240446","icon":"/logos/teams-v2/240446.png","slug":"uitm-fc","form":["-","-","-","-","-"]},{"short_name":"Cidade de Petaling Jaya FC","abbreviation":"PEJ","name":"Cidade de Petaling Jaya FC","id":"312232","team_id":"312232","icon":"/logos/teams-v2/312232.png","slug":"cidade-de-petaling-jaya-fc","form":["-","-","-","-","-"]},{"short_name":"PIB FC","abbreviation":"PIB","name":"PIB FC","id":"413697","team_id":"413697","icon":"/logos/teams-v2/413697.png","slug":"pib-fc","form":["-","-","-","-","-"]},{"short_name":"Kuching City","abbreviation":"KUC","name":"Kuching City FC","id":"413705","team_id":"413705","icon":"/logos/teams-v2/413705.png","slug":"kuching-city","form":["-","-","-","-","-"]},{"short_name":"Kelantan United FC","abbreviation":"KEL","name":"Kelantan United FC","id":"532665","team_id":"532665","icon":"/logos/teams-v2/532665.png","slug":"kelantan-united-fc","form":["-","-","-","-","-"]},{"short_name":"Cidade de Langkawi FC","abbreviation":"LAC","name":"Cidade de Langkawi FC","id":"546901","team_id":"546901","icon":"/logos/teams-v2/546901.png","slug":"cidade-de-langkawi-fc","form":["-","-","-","-","-"]},{"short_name":"Ultimate FC","abbreviation":"ULT","name":"Ultimate FC","id":"546903","team_id":"546903","icon":"/logos/teams-v2/546903.png","slug":"ultimate-fc","form":["-","-","-","-","-"]},{"short_name":"KSR Sains","abbreviation":"KSR","name":"KSR Sains","id":"546913","team_id":"546913","icon":"/logos/teams-v2/546913.png","slug":"ksr-sains","form":["-","-","-","-","-"]},{"short_name":"Harini FC","abbreviation":"HAR","name":"Harini FC","id":"682663","team_id":"682663","icon":"/logos/teams-v2/682663.png","slug":"harini-fc","form":["-","-","-","-","-"]},{"short_name":"Manjung City FC","abbreviation":"MAN","name":"Manjung City FC","id":"687677","team_id":"687677","icon":"/logos/teams-v2/687677.png","slug":"manjung-city-fc","form":["-","-","-","-","-"]},{"short_name":"Perlis United FC","abbreviation":"PER","name":"Perlis United FC","id":"687681","team_id":"687681","icon":"/logos/teams-v2/687681.png","slug":"perlis-united-fc","form":["-","-","-","-","-"]},{"short_name":"Projek Fam-MSN","abbreviation":"PRO","name":"Projek Fam-MSN","id":"778042","team_id":"778042","icon":"/logos/teams-v2/778042.png","slug":"projek-fam-msn","form":["-","-","-","-","-"]},{"short_name":"Brm FC","abbreviation":"BRM","name":"Brm FC","id":"878245","team_id":"878245","icon":"/logos/teams-v2/878245.png","slug":"brm-fc","form":["-","-","-","-","-"]},{"short_name":"Kijang Rangers FC","abbreviation":"KIJ","name":"Kijang Rangers FC","id":"878247","team_id":"878247","icon":"/logos/teams-v2/878247.png","slug":"kijang-rangers-fc","form":["-","-","-","-","-"]},{"short_name":"Tok Janggut Warriors FC","abbreviation":"TOK","name":"Tok Janggut Warriors FC","id":"882133","team_id":"882133","icon":"/logos/teams-v2/882133.png","slug":"tok-janggut-warriors-fc","form":["-","-","-","-","-"]},{"short_name":"Kinabalu Jaguar FC","abbreviation":"KIN","name":"Kinabalu Jaguar FC","id":"882135","team_id":"882135","icon":"/logos/teams-v2/882135.png","slug":"kinabalu-jaguar-fc","form":["-","-","-","-","-"]},{"short_name":"Bukit Tambun FC","abbreviation":"BUK","name":"Bukit Tambun FC","id":"882137","team_id":"882137","icon":"/logos/teams-v2/882137.png","slug":"bukit-tambun-fc","form":["-","-","-","-","-"]},{"short_name":"Respect FC","abbreviation":"RES","name":"Respect FC","id":"882163","team_id":"882163","icon":"/logos/teams-v2/882163.png","slug":"respect-fc","form":["-","-","-","-","-"]}],"summary_text":"Taça da FA, também conhecida como, Taça da FA 2022, é a liga de futebol profissional no(a) Malásia para men. Existem ao todo 32 times que competem pelo título todos os anos entre 11/03/2022 to 17/09/2022"}